setup.py
src/digimat/__init__.py
src/digimat.mqtt.egg-info/PKG-INFO
src/digimat.mqtt.egg-info/SOURCES.txt
src/digimat.mqtt.egg-info/dependency_links.txt
src/digimat.mqtt.egg-info/namespace_packages.txt
src/digimat.mqtt.egg-info/not-zip-safe
src/digimat.mqtt.egg-info/requires.txt
src/digimat.mqtt.egg-info/top_level.txt
src/digimat/mqtt/__init__.py
src/digimat/mqtt/mqtt.py