Metadata-Version: 1.0
Name: digimat.mqtt
Version: 0.1.11
Summary: Digimat MQTT
Home-page: http://www.digimat.ch
Author: Frederic Hess
Author-email: fhess@splust.ch
License: PSF
Platform: UNKNOWN
